{"global":0,"info":[{"version":100,"change":[]},{"version":99,"change":[]},{"version":98,"change":[]},{"version":97,"change":[]},{"version":96,"change":[{"flag":"suf","value":"h.json"}]},{"version":95},{"version":94},{"version":93,"change":[{"flag":"suf","value":"w.js"}]},{"version":92},{"version":91},{"version":90},{"version":89},{"version":88},{"version":87},{"version":86},{"version":85},{"version":84},{"version":83},{"version":82},{"version":81},{"version":80},{"version":79},{"version":78},{"version":77},{"version":76},{"version":75},{"version":74}]}